y5gg/__init__.py
y5gg/cli.py
y5gg/detect.py
y5gg/export.py
y5gg/helpers.py
y5gg/hubconf.py
y5gg/train.py
y5gg/val.py
y5gg/data/Argoverse.yaml
y5gg/data/GlobalWheat2020.yaml
y5gg/data/Objects365.yaml
y5gg/data/SKU-110K.yaml
y5gg/data/VOC.yaml
y5gg/data/VisDrone.yaml
y5gg/data/argoverse_hd.yaml
y5gg/data/coco.yaml
y5gg/data/coco128.yaml
y5gg/data/objects365.yaml
y5gg/data/visdrone.yaml
y5gg/data/voc.yaml
y5gg/data/xView.yaml
y5gg/data/hyps/hyp.finetune.yaml
y5gg/data/hyps/hyp.finetune_objects365.yaml
y5gg/data/hyps/hyp.scratch-high.yaml
y5gg/data/hyps/hyp.scratch-low.yaml
y5gg/data/hyps/hyp.scratch-med.yaml
y5gg/data/hyps/hyp.scratch-p6.yaml
y5gg/data/hyps/hyp.scratch.yaml
y5gg/data/images/bus.jpg
y5gg/data/images/zidane.jpg
y5gg/data/scripts/download_weights.sh
y5gg/data/scripts/get_argoverse_hd.sh
y5gg/data/scripts/get_coco.sh
y5gg/data/scripts/get_coco128.sh
y5gg/data/scripts/get_voc.sh
y5gg/models/__init__.py
y5gg/models/common.py
y5gg/models/experimental.py
y5gg/models/tf.py
y5gg/models/yolo.py
y5gg/models/yolov5l.yaml
y5gg/models/yolov5m.yaml
y5gg/models/yolov5n.yaml
y5gg/models/yolov5s.yaml
y5gg/models/yolov5x.yaml
y5gg/models/hub/anchors.yaml
y5gg/models/hub/yolov3-spp.yaml
y5gg/models/hub/yolov3-tiny.yaml
y5gg/models/hub/yolov3.yaml
y5gg/models/hub/yolov5-bifpn.yaml
y5gg/models/hub/yolov5-fpn.yaml
y5gg/models/hub/yolov5-p2.yaml
y5gg/models/hub/yolov5-p6.yaml
y5gg/models/hub/yolov5-p7.yaml
y5gg/models/hub/yolov5-panet.yaml
y5gg/models/hub/yolov5l6.yaml
y5gg/models/hub/yolov5m6.yaml
y5gg/models/hub/yolov5n6.yaml
y5gg/models/hub/yolov5s-ghost.yaml
y5gg/models/hub/yolov5s-transformer.yaml
y5gg/models/hub/yolov5s6.yaml
y5gg/models/hub/yolov5x6.yaml
y5gg/utils/__init__.py
y5gg/utils/activations.py
y5gg/utils/augmentations.py
y5gg/utils/autoanchor.py
y5gg/utils/callbacks.py
y5gg/utils/datasets.py
y5gg/utils/downloads.py
y5gg/utils/general.py
y5gg/utils/google_utils.py
y5gg/utils/loss.py
y5gg/utils/metrics.py
y5gg/utils/plots.py
y5gg/utils/torch_utils.py
y5gg-6.0.7.dist-info/LICENSE
y5gg-6.0.7.dist-info/METADATA
y5gg-6.0.7.dist-info/WHEEL
y5gg-6.0.7.dist-info/entry_points.txt
y5gg-6.0.7.dist-info/top_level.txt
y5gg-6.0.7.dist-info/RECORD
