Metadata-Version: 2.1
Name: y5gg
Version: 6.0.7
Summary: Packaged version of the Yolov5 object detector
Home-page: https://github.com/chienlq/y5gg
Author: 
License: GPL
Keywords: machine-learning,deep-learning,ml,pytorch,YOLO,object-detection,vision,YOLOv3,YOLOv4,YOLOv5
Platform: UNKNOWN
Classifier: Development Status :: 5 - Production/Stable
Classifier: License :: OSI Approved :: GNU General Public License (GPL)
Classifier: Operating System :: OS Independent
Classifier: Intended Audience :: Developers
Classifier: Intended Audience :: Science/Research
Classifier: Programming Language :: Python :: 3
Classifier: Programming Language :: Python :: 3.6
Classifier: Programming Language :: Python :: 3.7
Classifier: Programming Language :: Python :: 3.8
Classifier: Topic :: Software Development :: Libraries
Classifier: Topic :: Software Development :: Libraries :: Python Modules
Classifier: Topic :: Education
Classifier: Topic :: Scientific/Engineering
Classifier: Topic :: Scientific/Engineering :: Artificial Intelligence
Classifier: Topic :: Scientific/Engineering :: Image Recognition
Requires-Python: >=3.6
License-File: LICENSE
Requires-Dist: matplotlib (==3.3.4)
Requires-Dist: numpy (==1.19.5)
Requires-Dist: opencv-python (==4.2.0.34)
Requires-Dist: Pillow (==8.4.0)
Requires-Dist: PyYAML (==5.4.1)
Requires-Dist: requests (==2.24.0)
Requires-Dist: scipy (==1.5.4)
Requires-Dist: torch (==1.7.0)
Requires-Dist: torchvision (==0.8.1)
Requires-Dist: tqdm (==4.62.3)
Requires-Dist: tensorboard (==2.7.0)
Requires-Dist: pandas (==1.1.5)
Requires-Dist: seaborn (==0.11.2)
Requires-Dist: thop
Provides-Extra: tests
Requires-Dist: pytest ; extra == 'tests'
